tinapackage/__init__.py
tinapackage-0.1.dist-info/METADATA
tinapackage-0.1.dist-info/WHEEL
tinapackage-0.1.dist-info/top_level.txt
tinapackage-0.1.dist-info/RECORD
