Metadata-Version: 2.1
Name: tinapackage
Version: 0.1
Summary: Taiwan No. 1
Home-page: http://github.com/storborg/funniest
Author: Michael Chen
Author-email: tinalin5665@gmail.com
License: MIT
Platform: UNKNOWN
